jupyter_kubernetes/__init__.py
jupyter_kubernetes/__main__.py
jupyter_kubernetes/__version__.py
jupyter_kubernetes/application.py
jupyter_kubernetes/serverapplication.py
jupyter_kubernetes/handlers/__init__.py
jupyter_kubernetes/handlers/base.py
jupyter_kubernetes/handlers/config/__init__.py
jupyter_kubernetes/handlers/config/handler.py
jupyter_kubernetes/handlers/echo/__init__.py
jupyter_kubernetes/handlers/echo/handler.py
jupyter_kubernetes/handlers/index/__init__.py
jupyter_kubernetes/handlers/index/handler.py
jupyter_kubernetes/handlers/kubernetes/__init__.py
jupyter_kubernetes/handlers/kubernetes/handler.py
jupyter_kubernetes/handlers/ping/__init__.py
jupyter_kubernetes/handlers/ping/handler.py
jupyter_kubernetes/handlers/proxy/__init__.py
jupyter_kubernetes/handlers/proxy/handler.py
jupyter_kubernetes/handlers/relay/__init__.py
jupyter_kubernetes/handlers/relay/handler.py
jupyter_kubernetes/static/README.md
jupyter_kubernetes/templates/index.html
jupyter_kubernetes/tests/__init__.py
jupyter_kubernetes/tests/test_handlers.py
jupyter_kubernetes-0.0.5.data/data/etc/jupyter/jupyter_notebook_config.d/jupyter_kubernetes.json
jupyter_kubernetes-0.0.5.data/data/etc/jupyter/jupyter_server_config.d/jupyter_kubernetes.json
jupyter_kubernetes-0.0.5.dist-info/METADATA
jupyter_kubernetes-0.0.5.dist-info/WHEEL
jupyter_kubernetes-0.0.5.dist-info/entry_points.txt
jupyter_kubernetes-0.0.5.dist-info/licenses/LICENSE
jupyter_kubernetes-0.0.5.dist-info/RECORD
